sam_local_watcher/__init__.py
sam_local_watcher/cli.py
sam_local_watcher/watcher.py
sam_local_watcher-0.1.0.dist-info/licenses/LICENSE
sam_local_watcher-0.1.0.dist-info/METADATA
sam_local_watcher-0.1.0.dist-info/WHEEL
sam_local_watcher-0.1.0.dist-info/entry_points.txt
sam_local_watcher-0.1.0.dist-info/top_level.txt
sam_local_watcher-0.1.0.dist-info/RECORD
